norutil/__init__.py
norutil/config.py
norutil/core.py
norutil/definitions.py
norutil/helpers.py
norutil/util.py
norutil-0.0.2.dist-info/LICENSE
norutil-0.0.2.dist-info/METADATA
norutil-0.0.2.dist-info/WHEEL
norutil-0.0.2.dist-info/top_level.txt
norutil-0.0.2.dist-info/RECORD
