Metadata-Version: 2.1
Name: norutil
Version: 0.0.2
Summary: Prototype package for my personal development
Home-page: https://github.com/norabal/norutil
Author: Motoi Komatsu
Author-email: norabal.works@gmail.com
License: Copyright (c) 2018, Motoi Komatsu
Requires-Dist: nose
Requires-Dist: sphinx
Requires-Dist: twine
